Metadata-Version: 2.1
Name: compounding
Version: 0.1
Summary: For calculating compound interest
